cc/udp/__init__.py
cc/udp/core.py
cc.udp-2024.9.1.post1.dist-info/LICENSE
cc.udp-2024.9.1.post1.dist-info/METADATA
cc.udp-2024.9.1.post1.dist-info/WHEEL
cc.udp-2024.9.1.post1.dist-info/top_level.txt
cc.udp-2024.9.1.post1.dist-info/RECORD
