Metadata-Version: 2.1
Name: cc.udp
Version: 2024.9.1.post1
Summary: UDP helper function for robotics workload.
Home-page: https://github.com/uncertainty-cc/UDP-Python
Author: Uncertainty.
Author-email: t_k_233@outlook.email
Classifier: Programming Language :: Python :: 3
Classifier: License :: OSI Approved :: MIT License
Classifier: Operating System :: OS Independent
Requires-Python: >=3.8
License-File: LICENSE
Requires-Dist: numpy
Requires-Dist: cc-serializer
